MANIFEST.in
license.txt
pytimechart-record
pytimechart.desktop
readme.txt
setup.py
pytimechart.egg-info/PKG-INFO
pytimechart.egg-info/SOURCES.txt
pytimechart.egg-info/dependency_links.txt
pytimechart.egg-info/entry_points.txt
pytimechart.egg-info/namespace_packages.txt
pytimechart.egg-info/not-zip-safe
pytimechart.egg-info/requires.txt
pytimechart.egg-info/top_level.txt
timechart/__init__.py
timechart/actions.py
timechart/colors.py
timechart/model.py
timechart/plot.py
timechart/plugin.py
timechart/process_table.py
timechart/py2exe_wximports.py
timechart/timechart.py
timechart/tools.py
timechart/window.py
timechart/backends/__init__.py
timechart/backends/ftrace.py
timechart/backends/perf.py
timechart/backends/tracecmd.py
timechart/images/clear.png
timechart/images/gtkrc
timechart/images/hide.png
timechart/images/hide_onscreen.png
timechart/images/hide_others.png
timechart/images/images_license.txt
timechart/images/invert.png
timechart/images/select_all.png
timechart/images/show.png
timechart/images/toggle_auto_zoom_y.png
timechart/images/toggle_autohide.png
timechart/images/toggle_cpufreq.png
timechart/images/toggle_cpuidle.png
timechart/images/toggle_wakes.png
timechart/images/trace_text.png
timechart/images/unzoom.png
timechart/images/view_properties.png
timechart/images/zoom.png
timechart/plugins/__init__.py
timechart/plugins/cpuidle.py
timechart/plugins/irq.py
timechart/plugins/menu_select.py
timechart/plugins/runtime_pm.py
timechart/plugins/sched.py
timechart/plugins/spi.py
timechart/plugins/timers.py
timechart/plugins/wake_lock.py