Metadata-Version: 1.0
Name: pytimechart
Version: 0.9.2
Summary: Fast graphical exploration and visualisation for linux kernel traces
Home-page: http://gitorious.org/pytimechart
Author: Pierre Tardy
Author-email: tardyp@gmail.com
License: BSD
Download-URL: http://gitorious.org/pytimechart
Keywords: gui,ftrace,perf,trace-event
Platform: Windows
Platform: Linux
Platform: Mac OS-X
Platform: Unix
Platform: Solaris
Classifier: License :: OSI Approved :: BSD License
Classifier: Programming Language :: Python
Classifier: Topic :: Software Development :: Libraries :: Python Modules
Classifier: Operating System :: Microsoft :: Windows
Classifier: Operating System :: OS Independent
Classifier: Operating System :: POSIX
Classifier: Operating System :: Unix
Classifier: Intended Audience :: Developers
